gron/__init__.py
gron/__main__.py
gron/gron.py
gron/version.py
gron-1.4.0.dist-info/LICENSE
gron-1.4.0.dist-info/METADATA
gron-1.4.0.dist-info/WHEEL
gron-1.4.0.dist-info/entry_points.txt
gron-1.4.0.dist-info/top_level.txt
gron-1.4.0.dist-info/RECORD
