Metadata-Version: 2.1
Name: gron
Version: 1.4.0
Summary: Python library to grep JSON.
Author-email: Bastian Venthur <mail@venthur.de>
License: MIT License
Project-URL: Documentation, https://gron.readthedocs.io/
Project-URL: Source, https://github.com/venthur/python-gron
Project-URL: Changelog, https://github.com/venthur/python-gron/blob/master/CHANGELOG.md
Classifier: Development Status :: 5 - Production/Stable
Classifier: Intended Audience :: Developers
Classifier: License :: OSI Approved :: MIT License
Classifier: Programming Language :: Python :: 3
Requires-Python: >=3.10
License-File: LICENSE
Provides-Extra: dev
Requires-Dist: build ==1.2.1 ; extra == 'dev'
Requires-Dist: mkdocs ==1.6.0 ; extra == 'dev'
Requires-Dist: mkdocs-material ==9.5.33 ; extra == 'dev'
Requires-Dist: mkdocstrings[python] ==0.25.2 ; extra == 'dev'
Requires-Dist: mypy ==1.11.1 ; extra == 'dev'
Requires-Dist: pytest-cov ==5.0.0 ; extra == 'dev'
Requires-Dist: pytest ==8.3.2 ; extra == 'dev'
Requires-Dist: ruff ==0.6.2 ; extra == 'dev'
Requires-Dist: sphinx ==8.0.2 ; extra == 'dev'
Requires-Dist: twine ==5.1.1 ; extra == 'dev'
Requires-Dist: wheel ==0.44.0 ; extra == 'dev'
